vida_py/__init__.py
vida_py/util.py
vida_py/access/__init__.py
vida_py/access/models.py
vida_py/access/scripts.py
vida_py/basedata/__init__.py
vida_py/basedata/funcs.py
vida_py/basedata/models.py
vida_py/basedata/scripts.py
vida_py/basedata/views.py
vida_py/carcom/__init__.py
vida_py/carcom/funcs.py
vida_py/carcom/models.py
vida_py/carcom/scripts.py
vida_py/diag/__init__.py
vida_py/diag/funcs.py
vida_py/diag/models.py
vida_py/diag/scripts.py
vida_py/diag/views.py
vida_py/epc/__init__.py
vida_py/epc/models.py
vida_py/images/__init__.py
vida_py/images/models.py
vida_py/images/scripts.py
vida_py/service/__init__.py
vida_py/service/funcs.py
vida_py/service/models.py
vida_py/service/scripts.py
vida_py/session/__init__.py
vida_py/session/funcs.py
vida_py/session/models.py
vida_py/session/scripts.py
vida_py/timing/__init__.py
vida_py/timing/models.py
vida_py/timing/views.py
vida_py-0.1.7.dist-info/licenses/LICENSE
vida_py-0.1.7.dist-info/METADATA
vida_py-0.1.7.dist-info/WHEEL
vida_py-0.1.7.dist-info/top_level.txt
vida_py-0.1.7.dist-info/RECORD
