Metadata-Version: 2.4
Name: vida_py
Version: 0.1.7
Summary: Python interface for Volvo's VIDA databases.
Author-email: Kestin Goforth <kgoforth1503@gmail.com>
Maintainer-email: Kestin Goforth <kgoforth1503@gmail.com>
License: AGPL-3.0
Project-URL: homepage, https://github.com/kForth/vida_py
Project-URL: repository, https://github.com/kForth/vida_py.git
Project-URL: bugs, https://github.com/kForth/vida_py/issues
Keywords: VIDA,volvo
Classifier: Development Status :: 3 - Alpha
Classifier: Intended Audience :: Developers
Classifier: Topic :: Software Development :: Build Tools
Classifier: License :: OSI Approved :: GNU Affero General Public License v3 or later (AGPLv3+)
Classifier: Programming Language :: Python :: 3
Classifier: Programming Language :: Python :: 3.6
Classifier: Programming Language :: Python :: 3.7
Classifier: Programming Language :: Python :: 3.8
Classifier: Programming Language :: Python :: 3.9
Classifier: Programming Language :: Python :: 3.10
Classifier: Programming Language :: Python :: 3.11
Classifier: Programming Language :: Python :: 3.12
Requires-Python: >=3.6
License-File: LICENSE
Requires-Dist: click==8.1.8
Requires-Dist: pyodbc==5.2.0
Requires-Dist: SQLAlchemy==2.0.41
Provides-Extra: dev
Requires-Dist: pre-commit==4.1.0; extra == "dev"
Requires-Dist: bump-my-version==0.32.1; extra == "dev"
Dynamic: license-file
